try_build_package/__init__.py
try_build_package/math.py
try_build_package-0.0.1.dist-info/LICENSE
try_build_package-0.0.1.dist-info/METADATA
try_build_package-0.0.1.dist-info/WHEEL
try_build_package-0.0.1.dist-info/top_level.txt
try_build_package-0.0.1.dist-info/RECORD
